booleantools
