Metadata-Version: 1.2
Name: booleantools
Version: 0.4.2
Summary: A library for boolean functions, functions on GF(4), and Cellular Automata
Home-page: UNKNOWN
Author: Wesley Rogers, Andrew Penland
Author-email: wsrogers3@catamount.wcu.edu
License: MIT
Platform: UNKNOWN
Requires-Python: >=3
